{
  "games": [
    {
      "left": "team_a", 
      "left_score": 12, 
      "left_timeouts": [
        [
          11, 
          16
        ]
      ], 
      "right": "team_b", 
      "right_score": 25, 
      "right_timeouts": [], 
      "scores": [
        [
          0, 
          1
        ], 
        [
          0, 
          2
        ], 
        [
          0, 
          3
        ], 
        [
          0, 
          4
        ], 
        [
          0, 
          5
        ], 
        [
          0, 
          6
        ], 
        [
          1, 
          6
        ], 
        [
          1, 
          7
        ], 
        [
          2, 
          7
        ], 
        [
          3, 
          7
        ], 
        [
          4, 
          7
        ], 
        [
          4, 
          8
        ], 
        [
          5, 
          8
        ], 
        [
          6, 
          8
        ], 
        [
          6, 
          9
        ], 
        [
          7, 
          9
        ], 
        [
          8, 
          9
        ], 
        [
          9, 
          9
        ], 
        [
          9, 
          10
        ], 
        [
          10, 
          10
        ], 
        [
          10, 
          11
        ], 
        [
          10, 
          12
        ], 
        [
          11, 
          12
        ], 
        [
          11, 
          13
        ], 
        [
          11, 
          14
        ], 
        [
          11, 
          15
        ], 
        [
          11, 
          16
        ], 
        [
          11, 
          17
        ], 
        [
          11, 
          18
        ], 
        [
          11, 
          19
        ], 
        [
          11, 
          20
        ], 
        [
          12, 
          20
        ], 
        [
          12, 
          21
        ], 
        [
          12, 
          22
        ], 
        [
          12, 
          23
        ], 
        [
          12, 
          24
        ], 
        [
          12, 
          25
        ]
      ], 
      "server": "left"
    }, 
    {
      "left": "team_b", 
      "left_score": 25, 
      "left_timeouts": [], 
      "right": "team_a", 
      "right_score": 19, 
      "right_timeouts": [
        [
          8, 
          8
        ], 
        [
          15, 
          8
        ]
      ], 
      "scores": [
        [
          0, 
          1
        ], 
        [
          0, 
          2
        ], 
        [
          0, 
          3
        ], 
        [
          1, 
          3
        ], 
        [
          1, 
          4
        ], 
        [
          1, 
          5
        ], 
        [
          2, 
          5
        ], 
        [
          3, 
          5
        ], 
        [
          4, 
          5
        ], 
        [
          5, 
          5
        ], 
        [
          5, 
          6
        ], 
        [
          5, 
          7
        ], 
        [
          6, 
          7
        ], 
        [
          6, 
          8
        ], 
        [
          7, 
          8
        ], 
        [
          8, 
          8
        ], 
        [
          9, 
          8
        ], 
        [
          10, 
          8
        ], 
        [
          11, 
          8
        ], 
        [
          12, 
          8
        ], 
        [
          13, 
          8
        ], 
        [
          14, 
          8
        ], 
        [
          15, 
          8
        ], 
        [
          16, 
          8
        ], 
        [
          16, 
          9
        ], 
        [
          17, 
          9
        ], 
        [
          17, 
          10
        ], 
        [
          18, 
          10
        ], 
        [
          19, 
          10
        ], 
        [
          20, 
          10
        ], 
        [
          21, 
          10
        ], 
        [
          21, 
          11
        ], 
        [
          21, 
          12
        ], 
        [
          21, 
          13
        ], 
        [
          21, 
          14
        ], 
        [
          21, 
          15
        ], 
        [
          22, 
          15
        ], 
        [
          22, 
          16
        ], 
        [
          22, 
          17
        ], 
        [
          23, 
          17
        ], 
        [
          23, 
          18
        ], 
        [
          24, 
          18
        ], 
        [
          25, 
          18
        ], 
        [
          25, 
          19
        ]
      ], 
      "server": "left"
    }
  ], 
  "match_id": "09e0213a-d5ea-4bdb-ae15-bb177efa95e2", 
  "team_a": "Serve City", 
  "team_b": "Club 1", 
  "winner": "team_b"
}